lilypad/.fernignore
lilypad/__init__.py
lilypad/_configure.py
lilypad/context_managers.py
lilypad/exceptions.py
lilypad/sessions.py
lilypad/spans.py
lilypad/traces.py
lilypad/_opentelemetry/__init__.py
lilypad/_opentelemetry/_utils.py
lilypad/_opentelemetry/_opentelemetry_anthropic/__init__.py
lilypad/_opentelemetry/_opentelemetry_anthropic/patch.py
lilypad/_opentelemetry/_opentelemetry_anthropic/utils.py
lilypad/_opentelemetry/_opentelemetry_azure/__init__.py
lilypad/_opentelemetry/_opentelemetry_azure/patch.py
lilypad/_opentelemetry/_opentelemetry_azure/utils.py
lilypad/_opentelemetry/_opentelemetry_bedrock/__init__.py
lilypad/_opentelemetry/_opentelemetry_bedrock/patch.py
lilypad/_opentelemetry/_opentelemetry_bedrock/utils.py
lilypad/_opentelemetry/_opentelemetry_google_genai/__init__.py
lilypad/_opentelemetry/_opentelemetry_google_genai/patch.py
lilypad/_opentelemetry/_opentelemetry_google_genai/utils.py
lilypad/_opentelemetry/_opentelemetry_mistral/__init__.py
lilypad/_opentelemetry/_opentelemetry_mistral/patch.py
lilypad/_opentelemetry/_opentelemetry_mistral/utils.py
lilypad/_opentelemetry/_opentelemetry_openai/__init__.py
lilypad/_opentelemetry/_opentelemetry_openai/patch.py
lilypad/_opentelemetry/_opentelemetry_openai/utils.py
lilypad/_opentelemetry/_opentelemetry_outlines/__init__.py
lilypad/_opentelemetry/_opentelemetry_outlines/patch.py
lilypad/_opentelemetry/_opentelemetry_outlines/utils.py
lilypad/_opentelemetry/http/__init__.py
lilypad/_opentelemetry/http/auto_instrument.py
lilypad/_utils/__init__.py
lilypad/_utils/call_safely.py
lilypad/_utils/client.py
lilypad/_utils/closure.py
lilypad/_utils/config.py
lilypad/_utils/constants.py
lilypad/_utils/context_propagation.py
lilypad/_utils/fn_is_async.py
lilypad/_utils/function_cache.py
lilypad/_utils/functions.py
lilypad/_utils/json.py
lilypad/_utils/middleware.py
lilypad/_utils/mirascope_middleware_factory.py
lilypad/_utils/otel_debug.py
lilypad/_utils/serializer_registry.py
lilypad/_utils/settings.py
lilypad_sdk-0.10.4.dist-info/METADATA
lilypad_sdk-0.10.4.dist-info/WHEEL
lilypad_sdk-0.10.4.dist-info/entry_points.txt
lilypad_sdk-0.10.4.dist-info/licenses/LICENSE
lilypad_sdk-0.10.4.dist-info/RECORD
