Metadata-Version: 2.4
Name: lilypad-sdk
Version: 0.10.4
Dynamic: Description
Dynamic: Description-Content-Type
Summary: The official Python library for the Lilypad API
Project-URL: Homepage, https://github.com/Mirascope/lilypad
Project-URL: Repository, https://github.com/Mirascope/lilypad
Author-email: Mirascope <support@mirascope.com>
License-Expression: Apache-2.0
License-File: LICENSE
Classifier: Intended Audience :: Developers
Classifier: License :: OSI Approved :: Apache Software License
Classifier: Operating System :: MacOS
Classifier: Operating System :: Microsoft :: Windows
Classifier: Operating System :: OS Independent
Classifier: Operating System :: POSIX
Classifier: Operating System :: POSIX :: Linux
Classifier: Programming Language :: Python :: 3.10
Classifier: Programming Language :: Python :: 3.11
Classifier: Programming Language :: Python :: 3.12
Classifier: Topic :: Software Development :: Libraries :: Python Modules
Classifier: Typing :: Typed
Requires-Python: >=3.10
Requires-Dist: anyio<5,>=3.5.0
Requires-Dist: distro<2,>=1.7.0
Requires-Dist: httpx<1,>=0.23.0
Requires-Dist: libcst>=1.6.0
Requires-Dist: mirascope>=1.23.3
Requires-Dist: opentelemetry-api>=1.31.0
Requires-Dist: opentelemetry-instrumentation>=0.51b0
Requires-Dist: opentelemetry-propagator-b3>=1.31.0
Requires-Dist: opentelemetry-propagator-jaeger>=1.31.0
Requires-Dist: opentelemetry-sdk>=1.31.0
Requires-Dist: orjson>=2.0.1
Requires-Dist: pydantic-settings>=2.6.1
Requires-Dist: pydantic<3,>=2.10.6
Requires-Dist: ruff>=0.11.2
Requires-Dist: sniffio
Requires-Dist: typing-extensions<5,>=4.10
Provides-Extra: anthropic
Requires-Dist: anthropic>=0.36.0; extra == 'anthropic'
Provides-Extra: azure
Requires-Dist: aiohttp<4.0,>=3.10.5; extra == 'azure'
Requires-Dist: azure-ai-inference<2.0,>=1.0.0b9; extra == 'azure'
Provides-Extra: bedrock
Requires-Dist: aioboto3<14,>=13.1.1; extra == 'bedrock'
Requires-Dist: boto3-stubs[bedrock-runtime]<2,>=1.35.32; extra == 'bedrock'
Requires-Dist: boto3<2,>=1.34.70; extra == 'bedrock'
Requires-Dist: types-aioboto3[bedrock-runtime]<14,>=13.1.1; extra == 'bedrock'
Provides-Extra: cli
Requires-Dist: rich>=13.7.1; extra == 'cli'
Requires-Dist: typer>=0.15.2; extra == 'cli'
Provides-Extra: gemini
Requires-Dist: google-generativeai<1,>=0.4.0; extra == 'gemini'
Requires-Dist: pillow<11,>=10.4.0; extra == 'gemini'
Provides-Extra: google
Requires-Dist: google-genai<2,>=1.7.0; extra == 'google'
Requires-Dist: pillow<11,>=10.4.0; extra == 'google'
Requires-Dist: proto-plus>=1.24.0; extra == 'google'
Provides-Extra: mistral
Requires-Dist: mistralai<2,>=1.0.0; extra == 'mistral'
Provides-Extra: openai
Requires-Dist: openai>=1.57.0; extra == 'openai'
Provides-Extra: outlines
Requires-Dist: outlines>=0.1.11; extra == 'outlines'
Provides-Extra: sandbox-docker
Requires-Dist: docker>=7.1.0; extra == 'sandbox-docker'
Provides-Extra: vertex
Requires-Dist: google-cloud-aiplatform>=1.74.0; extra == 'vertex'
